{
"dialogOption":"custom",
"alertOption":"sheet",
"dialogTitle":"CHANNEL BOKEP UPDATE",
"dialogSubtitle":"Update now in my Channel to get New Feature!!",
"customDialogRound":"35",
"customDialogMainTxtColor":"#FFFFFF",
"customDialogBtnTxtColor":"#FFFFFF",
"customDialogBack":"#101010",
"customDialogAccent":"#1B8AF2",
"dialogBtnMain":"true",
"dialogBtnMainClick":"browser",
"dialogBtnMainTxt":"BOKEP NOW!!",
"openLinkMain":"https://xnxx.com",
"newVersion":"2.9",
"isCancelable":"false",
"isOneTime":"false",
"isOneTimeKey":"null",
"email":"xredz182@gmail.com"
}
